MiScan/__init__.py
MiScan/__main__.py
MiScan/cli.py
MiScan/core.py
MiScan/layers.py
MiScan/logging.py
MiScan/model.py
MiScan/dependency_data/13885fea_exon_cut_100bp_2sample.txt
MiScan/dependency_data/MISCAN.norm.trainPred.txt
MiScan/dependency_data/MISCAN.pat.trainPred.txt
MiScan/dependency_data/featureID.bed
MiScan/dependency_data/tcga_13885fea_exon_cut_100bp.bed
MiScan/utils/__init__.py
MiScan/utils/constants.py
MiScan/utils/files.py
MiScan/utils/util.py
MiScan-1.1.1.dist-info/LICENSE
MiScan-1.1.1.dist-info/METADATA
MiScan-1.1.1.dist-info/WHEEL
MiScan-1.1.1.dist-info/entry_points.txt
MiScan-1.1.1.dist-info/top_level.txt
MiScan-1.1.1.dist-info/RECORD
